{
	"schemaVersion": 1,
	"id": "${id}",
	"version": "${version}",
	"name": "${name}",
	"description": "${description}",
	"authors": [
		"FelixAgairu"
	],
	"contact": {
		"sources": "https://github.com/FelixAgairu/config-manager"
	},
	"license": "MPL2.0",
	"icon": "assets/config-manager/icon.png",
	"environment": "*",
	"entrypoints": {"main": []},
	"mixins": [],
	"depends": {
		"fabricloader": "${fabricLoaderVersion}",
		"minecraft": ">=${minecraftVersion}",
		"fabric-api": ">=${fabricVersion}"
	},
	"suggests": {}
}